{
  "id": "A-004",
  "status": "excluded",
  "filter_reason": "About airborne carbon nanotubes, drawing an analogy to asbestos; a different exposure entirely, with no talc/asbestos causation or exposure findings.",
  "summary": null,
  "retrieved": "2026-07-09",
  "pmid": "42392601",
  "title": "A Novel Sampling and Analytical Framework for Airborne Carbon Nanotubes.",
  "journal": "Analytical chemistry",
  "pub_date": "2026 Jul 02",
  "authors": "Davey HA et al.",
  "abstract": "Airborne carbon nanotubes (CNTs) present growing environmental and occupational health concerns. Like asbestos, CNT can deposit deep in the lungs and induce toxic effects, underscoring the need for accurate exposure metrics amid increasing global production. Current exposure assessment methods by the National Institute for Occupational Safety and Health (NIOSH) rely on mass-based measurements and indirect transmission electron microscopy (TEM), which often underestimate exposure, particularly for nanoscale fibers. To overcome these limitations, the objectives of this study were to develop a CNT-specific sampling and analysis method to improve fiber detection and characterization and validate its performance by comparing the novel diffusion-based sampler, Tsai Diffusion Sampler (TDS), with conventional approaches. Samplers were operated side-by-side under controlled conditions to ensure comparability. Furthermore, polycarbonate (PC) and mixed cellulose ester (MCE) filters were evaluated for all of the sampling configurations. CNTs collected onto filters and TEM grids were examined for their corresponding direct or indirect analysis. An automated image segmentation algorithm was applied to CNT images to ensure consistent fiber sizing and to support a count-based exposure metric. Results demonstrated that the TDS (which utilizes low flow rate) paired with PC filters most effectively captured individualized nanoscale fibers, enabling recovery of CNT structures of less than 100 nm that were underrepresented in compared methods. Aerosolized hydrophilic CNTs exhibited higher number concentrations than hydrophobic CNTs, while open-face samplers with MCE filters produced the highest mass concentrations. Importantly, these findings establish a reproducible, integrated sampling, and analytical framework that enhances CNT exposure assessment and supports refinement of occupational health guidelines.",
  "run_id": "R-001"
}
